kafka_client_decorator/__init__.py
kafka_client_decorator/client_producer.py
kafka_client_decorator/kafka_client.py
kafka_client_decorator-1.7.dist-info/LICENSE
kafka_client_decorator-1.7.dist-info/METADATA
kafka_client_decorator-1.7.dist-info/WHEEL
kafka_client_decorator-1.7.dist-info/top_level.txt
kafka_client_decorator-1.7.dist-info/RECORD
