Metadata-Version: 2.1
Name: kafka-client-decorator
Version: 1.7
Summary: A wrapper for confluent-kafka producer and consumer
Home-page: https://www.quantrium.ai/
Author: Quantrium
Author-email: firoz.mohammad@quantrium.ai
License: Quantrium PVT LTD
Keywords: confluent-kafka,Kafka-producer,Kafka-consumer
Requires-Python: >=3.6
License-File: LICENSE
Requires-Dist: confluent-kafka ==2.0.2
